MyFirstProject-0.0.1.dist-info/METADATA
MyFirstProject-0.0.1.dist-info/RECORD
MyFirstProject-0.0.1.dist-info/WHEEL
MyFirstProject-0.0.1.dist-info/top_level.txt
pa/__init__.py
pa/studylst.py
pb/__init__.py
pb/suiyi.py
