Metadata-Version: 2.1
Name: MyFirstProject
Version: 0.0.1
Summary: first
Home-page: UNKNOWN
Author: hf
Author-email: 
License: UNKNOWN
Platform: UNKNOWN
Classifier: License :: OSI Approved :: MIT License
Requires-Python: >=3.6
